pleiades/__init__.py
pleiades/__main__.py
pleiades/_version.py
pleiades/post_install.py
pleiades/core/__init__.py
pleiades/core/constants.py
pleiades/experimental/models.py
pleiades/nuclear/__init__.py
pleiades/nuclear/manager.py
pleiades/nuclear/models.py
pleiades/nuclear/isotopes/manager.py
pleiades/nuclear/isotopes/models.py
pleiades/processing/__init__.py
pleiades/processing/helper_ornl.py
pleiades/processing/models_ornl.py
pleiades/processing/normalization.py
pleiades/processing/normalization_ornl.py
pleiades/results/models.py
pleiades/sammy/__init__.py
pleiades/sammy/config.py
pleiades/sammy/factory.py
pleiades/sammy/interface.py
pleiades/sammy/parfile.py
pleiades/sammy/alphanumerics/__init__.py
pleiades/sammy/alphanumerics/angular_distribution.py
pleiades/sammy/alphanumerics/averages.py
pleiades/sammy/alphanumerics/bayes_solution.py
pleiades/sammy/alphanumerics/broadening.py
pleiades/sammy/alphanumerics/covariance_matrix_data.py
pleiades/sammy/alphanumerics/cross_section.py
pleiades/sammy/alphanumerics/endf.py
pleiades/sammy/alphanumerics/experimental_data_input.py
pleiades/sammy/alphanumerics/input_quantum_numbers.py
pleiades/sammy/alphanumerics/lpt.py
pleiades/sammy/alphanumerics/multiple_scattering_corrections.py
pleiades/sammy/alphanumerics/p_covariance_matrix_in.py
pleiades/sammy/alphanumerics/p_covariance_matrix_out.py
pleiades/sammy/alphanumerics/physical_constants.py
pleiades/sammy/alphanumerics/plot_file.py
pleiades/sammy/alphanumerics/r_matrix.py
pleiades/sammy/alphanumerics/sammy_alphanumerics.yaml
pleiades/sammy/alphanumerics/special_analysis.py
pleiades/sammy/alphanumerics/urr.py
pleiades/sammy/backends/__init__.py
pleiades/sammy/backends/docker.py
pleiades/sammy/backends/local.py
pleiades/sammy/backends/nova_ornl.py
pleiades/sammy/data/options.py
pleiades/sammy/fitting/config.py
pleiades/sammy/fitting/options.py
pleiades/sammy/io/data_manager.py
pleiades/sammy/io/inp_manager.py
pleiades/sammy/io/json_manager.py
pleiades/sammy/io/lpt_manager.py
pleiades_neutron-2.1.4.dist-info/licenses/LICENSE
pleiades_neutron-2.1.4.dist-info/METADATA
pleiades_neutron-2.1.4.dist-info/WHEEL
pleiades_neutron-2.1.4.dist-info/entry_points.txt
pleiades_neutron-2.1.4.dist-info/top_level.txt
pleiades_neutron-2.1.4.dist-info/RECORD
