Metadata-Version: 2.4
Name: pleiades-neutron
Version: 2.1.4
Summary: PLEIADES - Python Libraries Extensions for Isotopic Analysis via Detailed Examination of SAMMY
Author-email: "Alex M. Long" <alexlong@lanl.gov>, Tsviki Hirsh <tsviki.hirsh@gmail.com>, Chen Zhang <zhangc@ornl.gov>, Jean Bilheux <bilheuxjm@ornl.gov>
Maintainer-email: Chen Zhang <zhangc@ornl.gov>
License: LANL-Modified-MIT
Project-URL: homepage, https://github.com/lanl/PLEIADES
Project-URL: repository, https://github.com/lanl/PLEIADES
Project-URL: documentation, https://pleiades-sammy.readthedocs.io
Project-URL: issues, https://github.com/lanl/PLEIADES/issues
Keywords: neutron,resonance,cross-section
Requires-Python: <4.0,>=3.10
License-File: LICENSE
Requires-Dist: numpy
Requires-Dist: scipy
Requires-Dist: pandas
Requires-Dist: astropy
Requires-Dist: matplotlib
Requires-Dist: tifffile
Requires-Dist: jupyterlab
Requires-Dist: dxchange
Requires-Dist: pyyaml
Requires-Dist: scikit-image
Requires-Dist: pydantic
Requires-Dist: loguru
Provides-Extra: nova
Requires-Dist: nova-galaxy<0.8,>=0.7.4; extra == "nova"
Dynamic: license-file
